{"error":null,"body":"{\"categories\":[{\"name\":\"5k\",\"brackets\":[{\"id\":\"05c66269-371c-4345-8257-d4a7983d637c\",\"name\":\"Male 40 to 49\",\"type\":\"OPEN\",\"leaders\":[{\"name\":\"Ryan Aschbrenner\",\"bib\":\"647\",\"rank\":1,\"time\":\"00:18:00\",\"pace\":\"05:48\",\"pace_unit\":\"min\\/mi\",\"hometown\":\"NASHUA, NH\",\"registration_id\":\"956b6706-efe2-4ee3-89b3-9725b35873f0\",\"private\":0},{\"name\":\"David Evans\",\"bib\":\"1106\",\"rank\":2,\"time\":\"00:19:40\",\"pace\":\"06:20\",\"pace_unit\":\"min\\/mi\",\"hometown\":\"DOUGLASSVILLE, PA\",\"registration_id\":\"643c0280-cb6e-46b8-8c67-dcd8ecfaa344\",\"private\":0},{\"name\":\"Bill Comerford\",\"bib\":\"355\",\"rank\":3,\"time\":\"00:21:32\",\"pace\":\"06:56\",\"pace_unit\":\"min\\/mi\",\"hometown\":\"AMHERST, NH\",\"registration_id\":\"82f454b0-9dbd-4fc1-95ef-a727de25892b\",\"private\":0},{\"name\":\"Colin Crowley\",\"bib\":\"1046\",\"rank\":4,\"time\":\"00:21:47\",\"pace\":\"07:01\",\"pace_unit\":\"min\\/mi\",\"hometown\":\"BALLSTON SPA, NY\",\"registration_id\":\"4adf00b4-e303-4a4c-9063-4460d435e139\",\"private\":0},{\"name\":\"Timothy MacLean\",\"bib\":\"446\",\"rank\":5,\"time\":\"00:22:03\",\"pace\":\"07:06\",\"pace_unit\":\"min\\/mi\",\"hometown\":\"NASHUA, NH\",\"registration_id\":\"dd5803a7-8e2d-4b97-9af2-a7d2740c3563\",\"private\":0},{\"name\":\"Jason Hendricks\",\"bib\":\"1107\",\"rank\":6,\"time\":\"00:22:05\",\"pace\":\"07:07\",\"pace_unit\":\"min\\/mi\",\"hometown\":\"NASHUA, NH\",\"registration_id\":\"9d8cf5e3-f5f1-4720-b8ad-312ed8378e76\",\"private\":0},{\"name\":\"Roman Mrozek\",\"bib\":\"728\",\"rank\":7,\"time\":\"00:22:45\",\"pace\":\"07:20\",\"pace_unit\":\"min\\/mi\",\"hometown\":\"NASHUA, NH\",\"registration_id\":\"8018ed47-361d-4b29-928d-a27ea555a518\",\"private\":0},{\"name\":\"BJ Bottomley\",\"bib\":\"968\",\"rank\":8,\"time\":\"00:23:09\",\"pace\":\"07:27\",\"pace_unit\":\"min\\/mi\",\"hometown\":\"HOLLIS, NH\",\"registration_id\":\"f4a57b69-0259-4fd0-9d54-ab336b0bd7b0\",\"private\":0},{\"name\":\"Josh Burnett\",\"bib\":\"487\",\"rank\":9,\"time\":\"00:23:10\",\"pace\":\"07:28\",\"pace_unit\":\"min\\/mi\",\"hometown\":\"TYNGSBORO, MA\",\"registration_id\":\"e8f967cb-1403-40ad-a296-6affdebab060\",\"private\":0},{\"name\":\"Keith Pinette\",\"bib\":\"1109\",\"rank\":10,\"time\":\"00:23:12\",\"pace\":\"07:28\",\"pace_unit\":\"min\\/mi\",\"hometown\":\"MERRIMACK, NH\",\"registration_id\":\"b6c06e28-680b-4d11-88d3-d628da0fa7cc\",\"private\":0},{\"name\":\"Kevin Crowder\",\"bib\":\"354\",\"rank\":11,\"time\":\"00:23:25\",\"pace\":\"07:33\",\"pace_unit\":\"min\\/mi\",\"hometown\":\"HOLLIS, NH\",\"registration_id\":\"21605651-195f-4227-b94e-085d1b301d90\",\"private\":0},{\"name\":\"Jason Moriarty\",\"bib\":\"1052\",\"rank\":12,\"time\":\"00:23:33\",\"pace\":\"07:35\",\"pace_unit\":\"min\\/mi\",\"hometown\":\"WESTFORD, MA\",\"registration_id\":\"49dd2a1a-12ca-45b3-bad6-a91da6cf0d69\",\"private\":0},{\"name\":\"Joseph Bauer\",\"bib\":\"638\",\"rank\":13,\"time\":\"00:23:54\",\"pace\":\"07:42\",\"pace_unit\":\"min\\/mi\",\"hometown\":\"BROOKLINE, NH\",\"registration_id\":\"28fc3a23-927b-498f-92a8-621e61ce11bd\",\"private\":0},{\"name\":\"Joshua Gue\",\"bib\":\"139\",\"rank\":14,\"time\":\"00:23:57\",\"pace\":\"07:43\",\"pace_unit\":\"min\\/mi\",\"hometown\":\"MILFORD, NH\",\"registration_id\":\"5e5c0516-226e-44d1-bd8a-48623a883853\",\"private\":0},{\"name\":\"Dana Boudreau\",\"bib\":\"525\",\"rank\":15,\"time\":\"00:24:04\",\"pace\":\"07:45\",\"pace_unit\":\"min\\/mi\",\"hometown\":\"HUDSON, NH\",\"registration_id\":\"813dab70-b821-4934-86f6-4798d4f69e08\",\"private\":0},{\"name\":\"Jared O'Connor\",\"bib\":\"79\",\"rank\":16,\"time\":\"00:24:31\",\"pace\":\"07:54\",\"pace_unit\":\"min\\/mi\",\"hometown\":\"NASHUA, NH\",\"registration_id\":\"6cb59195-fac1-45ab-a267-706e44bf871f\",\"private\":0},{\"name\":\"John Erik Strom\",\"bib\":\"597\",\"rank\":17,\"time\":\"00:24:33\",\"pace\":\"07:54\",\"pace_unit\":\"min\\/mi\",\"hometown\":\"NASHUA, NH\",\"registration_id\":\"a77952cb-3d50-4a7c-90b9-be0b4daf8aaa\",\"private\":0},{\"name\":\"William Gramer\",\"bib\":\"904\",\"rank\":18,\"time\":\"00:25:00\",\"pace\":\"08:03\",\"pace_unit\":\"min\\/mi\",\"hometown\":\"TYNGSBORO, MA\",\"registration_id\":\"99150d5e-c3f8-4afb-9884-02e3bc573191\",\"private\":0},{\"name\":\"Dan Hickey\",\"bib\":\"490\",\"rank\":19,\"time\":\"00:25:01\",\"pace\":\"08:04\",\"pace_unit\":\"min\\/mi\",\"hometown\":\"NASHUA, NH\",\"registration_id\":\"a08048d3-0bdf-465c-8049-d96e987924c8\",\"private\":0},{\"name\":\"Matty Gregg\",\"bib\":\"789\",\"rank\":20,\"time\":\"00:25:02\",\"pace\":\"08:04\",\"pace_unit\":\"min\\/mi\",\"hometown\":\"NASHUA, NH\",\"registration_id\":\"5c58c8b3-637a-4bac-b4c6-53e84459436c\",\"private\":0},{\"name\":\"David Hediger\",\"bib\":\"1032\",\"rank\":21,\"time\":\"00:25:04\",\"pace\":\"08:05\",\"pace_unit\":\"min\\/mi\",\"hometown\":\"MINOT, ME\",\"registration_id\":\"a675df5a-8504-4ba9-9597-c8d3cac16439\",\"private\":0},{\"name\":\"Greg Richard\",\"bib\":\"119\",\"rank\":22,\"time\":\"00:25:30\",\"pace\":\"08:13\",\"pace_unit\":\"min\\/mi\",\"hometown\":\"Nashua, NH\",\"registration_id\":\"75ca2bd5-5866-4d8c-b0c3-674458a5824d\",\"private\":0},{\"name\":\"Matt Bryant\",\"bib\":\"592\",\"rank\":23,\"time\":\"00:25:55\",\"pace\":\"08:21\",\"pace_unit\":\"min\\/mi\",\"hometown\":\"NASHUA, NH\",\"registration_id\":\"ad0f1e0e-4126-4fd8-85aa-e927baea3d92\",\"private\":0},{\"name\":\"Matthew Hays\",\"bib\":\"535\",\"rank\":24,\"time\":\"00:26:00\",\"pace\":\"08:23\",\"pace_unit\":\"min\\/mi\",\"hometown\":\"NEW ROCHELLE, NY\",\"registration_id\":\"f095b9e0-aa63-4c6d-bfa4-13de9778a45b\",\"private\":0},{\"name\":\"Mike Mutnansky\",\"bib\":\"300\",\"rank\":25,\"time\":\"00:26:11\",\"pace\":\"08:26\",\"pace_unit\":\"min\\/mi\",\"hometown\":\"N CHELMSFORD, MA\",\"registration_id\":\"9ce4cc41-eaa2-44e0-b270-4015aa0a969c\",\"private\":0},{\"name\":\"Jason jdieffen@hotmail.com\",\"bib\":\"292\",\"rank\":26,\"time\":\"00:26:33\",\"pace\":\"08:33\",\"pace_unit\":\"min\\/mi\",\"hometown\":\"HOLLIS, NH\",\"registration_id\":\"22e6dfdc-ecf3-41f1-a038-572b574fd947\",\"private\":0},{\"name\":\"Kapil Bansal\",\"bib\":\"854\",\"rank\":27,\"time\":\"00:26:39\",\"pace\":\"08:35\",\"pace_unit\":\"min\\/mi\",\"hometown\":\"BERKELEY HTS, NJ\",\"registration_id\":\"381d7332-67fb-42fe-bcc6-bdac4c3e4bdf\",\"private\":0},{\"name\":\"Alex Kutschke\",\"bib\":\"367\",\"rank\":28,\"time\":\"00:29:13\",\"pace\":\"09:25\",\"pace_unit\":\"min\\/mi\",\"hometown\":\"NASHUA, NH\",\"registration_id\":\"4923a25f-07f1-4b69-ac78-6183a0f850e5\",\"private\":0},{\"name\":\"Todd Fryatt\",\"bib\":\"503\",\"rank\":29,\"time\":\"00:29:17\",\"pace\":\"09:26\",\"pace_unit\":\"min\\/mi\",\"hometown\":\"BOSTON, MA\",\"registration_id\":\"2844418c-4d12-4096-badb-31b3298a617d\",\"private\":0},{\"name\":\"Mathew Hall\",\"bib\":\"660\",\"rank\":30,\"time\":\"00:29:36\",\"pace\":\"09:32\",\"pace_unit\":\"min\\/mi\",\"hometown\":\"PEPPERELL, MA\",\"registration_id\":\"7ef2985d-9da6-44d4-b627-78208be176f8\",\"private\":0},{\"name\":\"Shawn Lowney\",\"bib\":\"909\",\"rank\":31,\"time\":\"00:29:40\",\"pace\":\"09:33\",\"pace_unit\":\"min\\/mi\",\"hometown\":\"RALEIGH, NC\",\"registration_id\":\"f6d099ea-183e-4058-b26c-367d15eea4ce\",\"private\":0},{\"name\":\"ajay krishnan\",\"bib\":\"860\",\"rank\":32,\"time\":\"00:30:06\",\"pace\":\"09:42\",\"pace_unit\":\"min\\/mi\",\"hometown\":\"WESTFORD, MA\",\"registration_id\":\"0fe31fb5-5688-47c9-b5f6-e9b5db8306da\",\"private\":0},{\"name\":\"Andrew Dratch\",\"bib\":\"16\",\"rank\":33,\"time\":\"00:30:21\",\"pace\":\"09:46\",\"pace_unit\":\"min\\/mi\",\"hometown\":\"NASHUA, NH\",\"registration_id\":\"70221590-c877-47e9-aa59-fdde5a29c250\",\"private\":0},{\"name\":\"Dan Scarpati\",\"bib\":\"440\",\"rank\":34,\"time\":\"00:30:28\",\"pace\":\"09:49\",\"pace_unit\":\"min\\/mi\",\"hometown\":\"NASHUA, NH\",\"registration_id\":\"793bcf35-6ea1-4346-9a1d-9654808471ba\",\"private\":0},{\"name\":\"Josh Chace\",\"bib\":\"178\",\"rank\":35,\"time\":\"00:31:03\",\"pace\":\"10:00\",\"pace_unit\":\"min\\/mi\",\"hometown\":\"Hudson, NH\",\"registration_id\":\"fb9b220c-0051-44f3-a703-3da9fbfdc38a\",\"private\":0},{\"name\":\"Thomas Markley\",\"bib\":\"321\",\"rank\":36,\"time\":\"00:31:09\",\"pace\":\"10:02\",\"pace_unit\":\"min\\/mi\",\"hometown\":\"NASHUA, NH\",\"registration_id\":\"8967dfff-9fe3-41ea-be72-c29dec100748\",\"private\":0},{\"name\":\"Erik Gray\",\"bib\":\"1121\",\"rank\":37,\"time\":\"00:31:09\",\"pace\":\"10:02\",\"pace_unit\":\"min\\/mi\",\"hometown\":\"SALEM, NH\",\"registration_id\":\"fcdd1879-0891-48a6-9079-868d766e4d0d\",\"private\":0},{\"name\":\"Keith Levesque\",\"bib\":\"57\",\"rank\":38,\"time\":\"00:31:21\",\"pace\":\"10:06\",\"pace_unit\":\"min\\/mi\",\"hometown\":\"HOLLIS, NH\",\"registration_id\":\"0e797637-6111-41bf-a2d9-8436dbcc6a08\",\"private\":0},{\"name\":\"Cliff Spinney\",\"bib\":\"546\",\"rank\":39,\"time\":\"00:31:28\",\"pace\":\"10:08\",\"pace_unit\":\"min\\/mi\",\"hometown\":\"NASHUA, NH\",\"registration_id\":\"77a7739b-78c2-4d15-8d9d-67eb495fa94b\",\"private\":0},{\"name\":\"Jason Paling\",\"bib\":\"1157\",\"rank\":40,\"time\":\"00:31:33\",\"pace\":\"10:10\",\"pace_unit\":\"min\\/mi\",\"hometown\":\"NASHUA, NH\",\"registration_id\":\"b4a65688-13f9-4112-97fb-7606288cee5e\",\"private\":0},{\"name\":\"Michael DuVarney\",\"bib\":\"218\",\"rank\":41,\"time\":\"00:31:50\",\"pace\":\"10:15\",\"pace_unit\":\"min\\/mi\",\"hometown\":\"NASHUA, NH\",\"registration_id\":\"d8dda2f0-5af1-44de-81d7-72cc1fe1a896\",\"private\":0},{\"name\":\"John Gureckis\",\"bib\":\"589\",\"rank\":42,\"time\":\"00:32:18\",\"pace\":\"10:24\",\"pace_unit\":\"min\\/mi\",\"hometown\":\"NASHUA, NH\",\"registration_id\":\"2faf1be2-cbc5-4237-ae0c-f4637f58059a\",\"private\":0},{\"name\":\"Michael Mannetta\",\"bib\":\"788\",\"rank\":43,\"time\":\"00:32:28\",\"pace\":\"10:27\",\"pace_unit\":\"min\\/mi\",\"hometown\":\"NASHUA, NH\",\"registration_id\":\"541fbd86-f761-43ae-a4a3-452b16f0311e\",\"private\":0},{\"name\":\"Jeremy Easton-Marks\",\"bib\":\"75\",\"rank\":44,\"time\":\"00:32:38\",\"pace\":\"10:31\",\"pace_unit\":\"min\\/mi\",\"hometown\":\"HOUSTON, TX\",\"registration_id\":\"04847683-bf57-451d-8ab4-4785d25baa14\",\"private\":0},{\"name\":\"Paul Casey\",\"bib\":\"567\",\"rank\":45,\"time\":\"00:32:41\",\"pace\":\"10:31\",\"pace_unit\":\"min\\/mi\",\"hometown\":\"NASHUA, NH\",\"registration_id\":\"ad7fd5f1-a2c7-4f6a-bd4f-5c8ef0146e0b\",\"private\":0},{\"name\":\"David Hooper\",\"bib\":\"495\",\"rank\":46,\"time\":\"00:33:06\",\"pace\":\"10:40\",\"pace_unit\":\"min\\/mi\",\"hometown\":\"NASHUA, NH\",\"registration_id\":\"9570c89a-bfbc-43d9-99bc-040021952166\",\"private\":0},{\"name\":\"Doug Fischer\",\"bib\":\"331\",\"rank\":47,\"time\":\"00:33:13\",\"pace\":\"10:42\",\"pace_unit\":\"min\\/mi\",\"hometown\":\"NASHUA, NH\",\"registration_id\":\"22a296d8-ddc5-4535-9f8e-bcae1c09b633\",\"private\":0},{\"name\":\"Ben Sommers\",\"bib\":\"92\",\"rank\":48,\"time\":\"00:33:31\",\"pace\":\"10:48\",\"pace_unit\":\"min\\/mi\",\"hometown\":\"Nashua, NH\",\"registration_id\":\"0fcc3b9a-af57-40be-a9b4-022859af8dfb\",\"private\":0},{\"name\":\"Jeff Bradshaw\",\"bib\":\"678\",\"rank\":49,\"time\":\"00:33:42\",\"pace\":\"10:51\",\"pace_unit\":\"min\\/mi\",\"hometown\":\"HUDSON, NH\",\"registration_id\":\"95134b62-fba4-4519-b38d-e8c264eca7f1\",\"private\":0},{\"name\":\"Charles Brisk\",\"bib\":\"117\",\"rank\":50,\"time\":\"00:35:14\",\"pace\":\"11:21\",\"pace_unit\":\"min\\/mi\",\"hometown\":\"NASHUA, NH\",\"registration_id\":\"c091a398-a027-4177-921c-3ac0e17dba62\",\"private\":0},{\"name\":\"Scott Parillo\",\"bib\":\"29\",\"rank\":51,\"time\":\"00:35:37\",\"pace\":\"11:28\",\"pace_unit\":\"min\\/mi\",\"hometown\":\"HUDSON, NH\",\"registration_id\":\"e33f329d-1467-4d81-8726-cc9cad5ce041\",\"private\":0},{\"name\":\"Brian Dowell\",\"bib\":\"227\",\"rank\":52,\"time\":\"00:37:36\",\"pace\":\"12:06\",\"pace_unit\":\"min\\/mi\",\"hometown\":\"NASHUA, NH\",\"registration_id\":\"1a8cb742-abf7-4ea3-842d-dec84e969b2b\",\"private\":0},{\"name\":\"Thomas Wappat\",\"bib\":\"420\",\"rank\":53,\"time\":\"00:37:37\",\"pace\":\"12:07\",\"pace_unit\":\"min\\/mi\",\"hometown\":\"NEWBURGH, NY\",\"registration_id\":\"03b57d7a-3b24-40f7-8d38-fbc16a8f05a5\",\"private\":0},{\"name\":\"Mike Oconnor\",\"bib\":\"622\",\"rank\":54,\"time\":\"00:37:38\",\"pace\":\"12:07\",\"pace_unit\":\"min\\/mi\",\"hometown\":\"NASHUA, NH\",\"registration_id\":\"c3a67e1c-8410-4492-898e-0b0b6cd6cb95\",\"private\":0},{\"name\":\"Robert Sisson\",\"bib\":\"67\",\"rank\":55,\"time\":\"00:37:43\",\"pace\":\"12:09\",\"pace_unit\":\"min\\/mi\",\"hometown\":\"NASHUA, NH\",\"registration_id\":\"22220078-4a27-47cd-895c-2dec39ccb04d\",\"private\":0},{\"name\":\"Kelly Gentry\",\"bib\":\"960\",\"rank\":56,\"time\":\"00:37:44\",\"pace\":\"12:09\",\"pace_unit\":\"min\\/mi\",\"hometown\":\"NASHUA, NH\",\"registration_id\":\"5253de31-3d63-4697-b5fe-55be001b645f\",\"private\":0},{\"name\":\"Brian Parente\",\"bib\":\"734\",\"rank\":57,\"time\":\"00:37:46\",\"pace\":\"12:10\",\"pace_unit\":\"min\\/mi\",\"hometown\":\"NASHUA, NH\",\"registration_id\":\"b1591170-3b90-401d-9b97-3b13504a1b7d\",\"private\":0},{\"name\":\"Paul Hill\",\"bib\":\"31\",\"rank\":58,\"time\":\"00:37:47\",\"pace\":\"12:10\",\"pace_unit\":\"min\\/mi\",\"hometown\":\"MERRIMACK, NH\",\"registration_id\":\"517ad9ed-66f6-4d87-a745-2e5d0b72255a\",\"private\":0},{\"name\":\"John Hosking\",\"bib\":\"803\",\"rank\":59,\"time\":\"00:38:18\",\"pace\":\"12:20\",\"pace_unit\":\"min\\/mi\",\"hometown\":\"HOLLIS, NH\",\"registration_id\":\"ed6bb268-3c64-405f-b4db-d712deff3f47\",\"private\":0},{\"name\":\"Mark Herlihy\",\"bib\":\"59\",\"rank\":60,\"time\":\"00:38:25\",\"pace\":\"12:22\",\"pace_unit\":\"min\\/mi\",\"hometown\":\"NASHUA, NH\",\"registration_id\":\"aea9ce72-8993-49bd-8ab2-9c75d0183c02\",\"private\":0},{\"name\":\"Jake Pritchard\",\"bib\":\"384\",\"rank\":61,\"time\":\"00:38:27\",\"pace\":\"12:23\",\"pace_unit\":\"min\\/mi\",\"hometown\":\"NASHUA, NH\",\"registration_id\":\"0b5c1c6d-e842-439b-823d-dec739820ff9\",\"private\":0},{\"name\":\"Tim DiNicola\",\"bib\":\"699\",\"rank\":62,\"time\":\"00:40:42\",\"pace\":\"13:06\",\"pace_unit\":\"min\\/mi\",\"hometown\":\"DUNSTABLE, MA\",\"registration_id\":\"e93fa77e-6a70-4207-a0ce-863595b2de8f\",\"private\":0},{\"name\":\"Johnny isenberger\",\"bib\":\"834\",\"rank\":63,\"time\":\"00:41:51\",\"pace\":\"13:28\",\"pace_unit\":\"min\\/mi\",\"hometown\":\"TYNGSBORO, MA\",\"registration_id\":\"a180646c-09ca-41ec-98e4-418a367ab31d\",\"private\":0},{\"name\":\"Shaun Nelson\",\"bib\":\"416\",\"rank\":64,\"time\":\"00:42:31\",\"pace\":\"13:41\",\"pace_unit\":\"min\\/mi\",\"hometown\":\"NASHUA, NH\",\"registration_id\":\"bbe30205-d844-49d5-9ac0-942d6e1bbb9d\",\"private\":0},{\"name\":\"Matt Trombley\",\"bib\":\"150\",\"rank\":65,\"time\":\"00:43:06\",\"pace\":\"13:53\",\"pace_unit\":\"min\\/mi\",\"hometown\":\"BROOKLINE, NH\",\"registration_id\":\"d2f7fdaa-180e-4cc8-9913-5305cf675cda\",\"private\":0},{\"name\":\"Jon Shields\",\"bib\":\"923\",\"rank\":66,\"time\":\"00:43:19\",\"pace\":\"13:57\",\"pace_unit\":\"min\\/mi\",\"hometown\":\"NASHUA, NH\",\"registration_id\":\"97a05c1c-00da-4947-bffb-99ce7a5d2407\",\"private\":0},{\"name\":\"Thomas Scherpa\",\"bib\":\"766\",\"rank\":67,\"time\":\"00:44:45\",\"pace\":\"14:24\",\"pace_unit\":\"min\\/mi\",\"hometown\":\"Sullivan, NH\",\"registration_id\":\"998375ff-40b9-4d65-bd53-4faa7b5af06a\",\"private\":0},{\"name\":\"Raymond Thibault\",\"bib\":\"719\",\"rank\":68,\"time\":\"00:45:50\",\"pace\":\"14:45\",\"pace_unit\":\"min\\/mi\",\"hometown\":\"GROTON, MA\",\"registration_id\":\"fff62545-e8d6-4c45-acef-7aaa93c086df\",\"private\":0},{\"name\":\"Joe Ferry\",\"bib\":\"208\",\"rank\":69,\"time\":\"00:47:33\",\"pace\":\"15:19\",\"pace_unit\":\"min\\/mi\",\"hometown\":\"LIVINGSTON, NJ\",\"registration_id\":\"427dc696-ce0c-4755-812e-4cfeaa742307\",\"private\":0},{\"name\":\"Wayne St.Martin\",\"bib\":\"1145\",\"rank\":70,\"time\":\"00:51:58\",\"pace\":\"16:44\",\"pace_unit\":\"min\\/mi\",\"hometown\":\"WOBURN, MA\",\"registration_id\":\"a0548b5e-2e14-43cc-9d23-92f2a851a194\",\"private\":0},{\"name\":\"Daniel Rube\",\"bib\":\"341\",\"rank\":71,\"time\":\"00:54:00\",\"pace\":\"17:23\",\"pace_unit\":\"min\\/mi\",\"hometown\":\"NASHUA, NH\",\"registration_id\":\"56b100ac-a67d-41a6-958c-167bd1beb73d\",\"private\":0},{\"name\":\"Jacob Rube\",\"bib\":\"441\",\"rank\":72,\"time\":\"00:54:46\",\"pace\":\"17:38\",\"pace_unit\":\"min\\/mi\",\"hometown\":\"NASHUA, NH\",\"registration_id\":\"424f981f-b943-4937-bdac-8157d45671ad\",\"private\":0},{\"name\":\"Jonathan Graves\",\"bib\":\"346\",\"rank\":73,\"time\":\"00:54:57\",\"pace\":\"17:41\",\"pace_unit\":\"min\\/mi\",\"hometown\":\"PHILADELPHIA, PA\",\"registration_id\":\"d6fa063b-d2d8-4678-82e8-f0960c4be5a5\",\"private\":0},{\"name\":\"Marco Barbosa\",\"bib\":\"1103\",\"rank\":74,\"time\":\"00:55:11\",\"pace\":\"17:46\",\"pace_unit\":\"min\\/mi\",\"hometown\":\"WAYLAND, MA\",\"registration_id\":\"1f713fdd-8299-4c81-8797-32af07aeffc8\",\"private\":0},{\"name\":\"Richard Gaschnig\",\"bib\":\"540\",\"rank\":75,\"time\":\"00:57:22\",\"pace\":\"18:28\",\"pace_unit\":\"min\\/mi\",\"hometown\":\"NASHUA, NH\",\"registration_id\":\"b7455d40-c6f3-412f-93a4-70027671c072\",\"private\":0},{\"name\":\"James Eaton\",\"bib\":\"772\",\"rank\":76,\"time\":\"00:57:50\",\"pace\":\"18:37\",\"pace_unit\":\"min\\/mi\",\"hometown\":\"NASHUA, NH\",\"registration_id\":\"a1749956-cca7-43d4-acd1-36525e9b5749\",\"private\":0},{\"name\":\"Torrick Moore\",\"bib\":\"431\",\"rank\":77,\"time\":\"00:58:51\",\"pace\":\"18:57\",\"pace_unit\":\"min\\/mi\",\"hometown\":\"NASHUA, NH\",\"registration_id\":\"983e3f38-0d78-4f4b-9904-b6a21b004a0b\",\"private\":0},{\"name\":\"Allan Graves\",\"bib\":\"344\",\"rank\":78,\"time\":\"01:01:22\",\"pace\":\"19:46\",\"pace_unit\":\"min\\/mi\",\"hometown\":\"NASHUA, NH\",\"registration_id\":\"1d865690-426c-4417-a315-c6abf33aa796\",\"private\":0},{\"name\":\"Mike Davis\",\"bib\":\"280\",\"rank\":79,\"time\":\"01:06:39\",\"pace\":\"21:28\",\"pace_unit\":\"min\\/mi\",\"hometown\":\"HUDSON, NH\",\"registration_id\":\"1a65c954-e1e1-4434-98d9-6a43a5b64012\",\"private\":0}]}]}],\"provider\":1}","lastUpdateDate":"2025-03-20T03:42:10Z","payload":{"pathParameters":{"raceName":"b1092b6e-2aa9-4204-970a-eb648ffd73a3"},"queryStringParameters":{"bracket_id":"05c66269-371c-4345-8257-d4a7983d637c","page":"1"}}}